README.rst
setup.py
HierMat/__init__.py
HierMat/block_cluster_tree.py
HierMat/cluster.py
HierMat/cluster_tree.py
HierMat/cuboid.py
HierMat/grid.py
HierMat/hmat.py
HierMat/rmat.py
HierMat/splitable.py
HierMat/utils.py
HierMat.egg-info/PKG-INFO
HierMat.egg-info/SOURCES.txt
HierMat.egg-info/dependency_links.txt
HierMat.egg-info/top_level.txt
HierMat/examples/__init__.py
HierMat/examples/model_1d.py