Metadata-Version: 1.1
Name: HierMat
Version: 0.8.0
Summary: Framework for Hierarchical Matrices
Home-page: http://hierarchicalmatrices.readthedocs.io/en/latest/index.html
Author: Markus Neumann
Author-email: markus.neumann@math.uzh.ch
License: GNU GPL v3
Download-URL: https://github.com/maekke97/HierarchicalMatrices
Platform: UNKNOWN
Requires: numpy
Requires: matplotlib
Requires: scipy
